MANIFEST.in
README.md
setup.py
cdx/__init__.py
cdx/cdx.py
cdx.egg-info/PKG-INFO
cdx.egg-info/SOURCES.txt
cdx.egg-info/dependency_links.txt
cdx.egg-info/entry_points.txt
cdx.egg-info/not-zip-safe
cdx.egg-info/top_level.txt