Metadata-Version: 1.0
Name: cdx
Version: 1.2.5
Summary: change dirpath or open a url by bookmark fast in terminal
Home-page: https://github.com/ZhangLijuncn/cdx
Author: lijun
Author-email: zhanglijuncn@outlook.com
License: MIT
Platform: UNKNOWN
